{
  "moduleName": "Slack / Admin Teams / List Admins",
  "version": "0.0.0",
  "description": "List all of the admins on a given workspace.",
  "keywords": [],
  "cacheMode": "always",
  "evalMode": "manual",
  "params": {
    "auth": {
      "schema": {
        "type": "any",
        "optional": true,
        "description": "Any supported Slack token (bot, workflow, user).\nNote: not all operations are supported with different token types.\n"
      },
      "advanced": false,
      "hideValue": true
    },
    "limit": {
      "schema": {
        "type": "number",
        "optional": true,
        "description": "The maximum number of items to return."
      },
      "advanced": true,
      "hideValue": false
    },
    "cursor": {
      "schema": {
        "type": "string",
        "optional": true,
        "description": "Set `cursor` to `next_cursor` returned by the previous call to list items in the next page."
      },
      "advanced": true,
      "hideValue": false
    },
    "teamId": {
      "schema": {
        "type": "string",
        "optional": true,
        "description": ""
      },
      "advanced": false,
      "hideValue": false
    }
  },
  "result": {
    "schema": {
      "type": "any"
    },
    "async": true
  },
  "attributes": {
    "externalDocs": "https://api.slack.com/methods/admin.teams.admins.list",
    "codeHash": "2eb409ccf5ad83b1d5c49d47d9607b2615d8a4a68dea12d624a5bcd70ffb65da"
  }
}