{
  "moduleName": "Slack / Usergroups / Enable",
  "version": "0.0.0",
  "description": "Enable a User Group",
  "keywords": [],
  "cacheMode": "always",
  "evalMode": "manual",
  "params": {
    "auth": {
      "schema": {
        "type": "any",
        "optional": true,
        "description": "Any supported Slack token (bot, workflow, user).\nNote: not all operations are supported with different token types.\n"
      },
      "advanced": false,
      "hideValue": true
    },
    "includeCount": {
      "schema": {
        "type": "boolean",
        "optional": true,
        "description": "Include the number of users in the User Group."
      },
      "advanced": true,
      "hideValue": false
    },
    "usergroup": {
      "schema": {
        "type": "string",
        "optional": true,
        "description": "The encoded ID of the User Group to enable."
      },
      "advanced": false,
      "hideValue": false
    }
  },
  "result": {
    "schema": {
      "type": "any"
    },
    "async": true
  },
  "attributes": {
    "externalDocs": "https://api.slack.com/methods/usergroups.enable",
    "codeHash": "8253bdb2b69a6cabacdde9be5d7aeb8dcd83a2a202c7b3a6a15011c58250a1aa"
  }
}