{
  "moduleName": "StabilityAI / User / Balance / Get",
  "version": "0.0.0",
  "description": "Get the credit balance of the account/organization associated with the API key",
  "keywords": [],
  "cacheMode": "always",
  "evalMode": "manual",
  "params": {
    "auth": {
      "schema": {
        "type": "string",
        "description": "Your [Stability API key](https://platform.stability.ai/account/keys), used to authenticate your requests. Although you may have multiple keys in your account, you should use the same key for all requests to this API."
      },
      "advanced": false,
      "hideValue": false
    },
    "organization": {
      "schema": {
        "type": "string",
        "optional": true,
        "description": "Allows for requests to be scoped to an organization other than the user's default.  If not provided, the user's default organization will be used."
      },
      "advanced": true,
      "hideValue": false
    },
    "stabilityClientId": {
      "schema": {
        "type": "string",
        "optional": true,
        "description": "Used to identify the source of requests, such as the client application or sub-organization. Optional, but recommended for organizational clarity."
      },
      "advanced": true,
      "hideValue": false
    },
    "stabilityClientVersion": {
      "schema": {
        "type": "string",
        "optional": true,
        "description": "Used to identify the version of the application or service making the requests. Optional, but recommended for organizational clarity."
      },
      "advanced": true,
      "hideValue": false
    }
  },
  "result": {
    "schema": {
      "type": "any"
    },
    "async": true
  },
  "attributes": {
    "externalDocs": "",
    "codeHash": "27a0a6ae4a58ef2aa4b9e8b797d429f476f2482c1c39c4d3313c5f61184b28af"
  }
}