{
  "moduleName": "Gmail / Users / Settings / Get POP",
  "version": "0.0.0",
  "description": "Gets POP settings.",
  "keywords": [],
  "cacheMode": "always",
  "evalMode": "manual",
  "params": {
    "accessToken": {
      "schema": {
        "type": "any",
        "optional": true,
        "description": "OAuth 2 access token. Most APIs require `https://mail.google.com/` scope. Google Auth / Service Account Token can be used to obtain a valid access token."
      },
      "advanced": false,
      "hideValue": true
    },
    "apiKey": {
      "schema": {
        "type": "any",
        "optional": true,
        "description": "API key can be generated in Google Developer Console in APIs & Services section. Leave blank if OAuth access token is used."
      },
      "advanced": true,
      "hideValue": true
    },
    "userId": {
      "schema": {
        "type": "string",
        "description": "User's email address. The special value \"me\" can be used to indicate the authenticated user."
      },
      "advanced": false,
      "hideValue": false
    }
  },
  "result": {
    "schema": {
      "type": "any"
    },
    "async": true
  },
  "attributes": {
    "externalDocs": "https://developers.google.com/gmail/api/reference/rest",
    "codeHash": "94ca9f865c8cf8a740453c6a86cfda4f50e71622c5c3397ef53b6acdbbfa49a2"
  }
}