{
  "moduleName": "Xero / User / Get",
  "version": "0.0.0",
  "description": "Retrieves a specific user",
  "keywords": [],
  "cacheMode": "always",
  "evalMode": "manual",
  "params": {
    "accessToken": {
      "schema": {
        "type": "any",
        "description": "OAuth 2 access token."
      },
      "advanced": false,
      "hideValue": true
    },
    "xeroTenantId": {
      "schema": {
        "type": "string",
        "description": "Xero identifier for Tenant"
      },
      "advanced": false,
      "hideValue": false
    },
    "userId": {
      "schema": {
        "type": "string",
        "description": "Unique identifier for a User"
      },
      "advanced": false,
      "hideValue": false
    }
  },
  "result": {
    "schema": {
      "type": "any"
    },
    "async": true
  },
  "attributes": {
    "externalDocs": "https://developer.xero.com/documentation/api/accounting/overview",
    "codeHash": "ef3103f7a665ff54305ef7ff8dcb95c6fc8498655098c25503de726032b548e9"
  }
}