{
  "moduleName": "GitHub / Repos / User Access Restrictions / Add",
  "version": "0.0.0",
  "description": "Protected branches are available in public repositories with GitHub Free and GitHub Free for organizations, and in public and private repositories with GitHub Pro, GitHub Team, GitHub Enterprise Cloud, and GitHub Enterprise Server. For more information, see [GitHub's products](https://docs.github.com/github/getting-started-with-github/githubs-products) in the GitHub Help documentation.\n\nGrants the specified people push access for this branch.\n\n| Type    | Description                                                                                                                   |\n| ------- | ----------------------------------------------------------------------------------------------------------------------------- |\n| `array` | Usernames for people who can have push access. **Note**: The list of users, apps, and teams in total is limited to 100 items. |",
  "keywords": [],
  "cacheMode": "always",
  "evalMode": "manual",
  "params": {
    "accessToken": {
      "schema": {
        "type": "any",
        "description": "GitHub Access Token"
      },
      "advanced": false,
      "hideValue": true
    },
    "owner": {
      "schema": {
        "type": "string",
        "description": "The account owner of the repository. The name is not case sensitive."
      },
      "advanced": false,
      "hideValue": false
    },
    "repo": {
      "schema": {
        "type": "string",
        "description": "The name of the repository without the `.git` extension. The name is not case sensitive."
      },
      "advanced": false,
      "hideValue": false
    },
    "branch": {
      "schema": {
        "type": "string",
        "description": "The name of the branch. Cannot contain wildcard characters. To use wildcard characters in branch names, use [the GraphQL API](https://docs.github.com/graphql)."
      },
      "advanced": false,
      "hideValue": false
    },
    "users": {
      "schema": {
        "type": "array",
        "items": {
          "type": "any"
        },
        "description": "The username for users"
      },
      "advanced": false,
      "hideValue": false
    }
  },
  "result": {
    "schema": {
      "type": "any"
    },
    "async": true
  },
  "attributes": {
    "externalDocs": "https://docs.github.com/rest/branches/branch-protection#add-user-access-restrictions",
    "codeHash": "489412f8e48104ba6da49774c2b84ff2109624ffa9a7029370bf6c1705a4cf60"
  }
}